Metadata-Version: 2.1
Name: whitespace2
Version: 1.0.0
Summary: An interpreter written in Python for the imperative, stack-backed language called Whitespace
Home-page: https://github.com/rzuckerm/whitespace-python
License: LICENSE
Author: rzuckerm
Requires-Python: >=3.8,<4.0
Classifier: Development Status :: 5 - Production/Stable
Classifier: License :: OSI Approved :: MIT License
Classifier: License :: Other/Proprietary License
Classifier: Operating System :: OS Independent
Classifier: Programming Language :: Python :: 3
Classifier: Programming Language :: Python :: 3.8
Classifier: Programming Language :: Python :: 3.9
Classifier: Programming Language :: Python :: 3.10
Classifier: Programming Language :: Python :: 3.11
Classifier: Programming Language :: Python :: 3.12
Project-URL: Bug Tracker, https://github.com/rzuckerm/whitespace-python/issues
Project-URL: Changelog, https://github.com/rzuckerm/whitespace-python/blob/master/CHANGELOG.rst
